keypair_permissions/__init__.py
keypair_permissions/__version__.py
keypair_permissions/admin.py
keypair_permissions/apps.py
keypair_permissions/crypto.py
keypair_permissions/exceptions.py
keypair_permissions/mixins.py
keypair_permissions/models.py
keypair_permissions/permissions.py
drf_keypair_permissions-1.0.5.dist-info/LICENSE
drf_keypair_permissions-1.0.5.dist-info/METADATA
drf_keypair_permissions-1.0.5.dist-info/WHEEL
drf_keypair_permissions-1.0.5.dist-info/top_level.txt
drf_keypair_permissions-1.0.5.dist-info/RECORD
