Metadata-Version: 2.1
Name: drf-keypair-permissions
Version: 1.0.5
Summary: Crypto Keypair Authorization for Django Rest Framework
Home-page: https://github.com/backupbrain/drf-keypair-permissions
Author: Adonis Gaitatzis
Author-email: backupbrain@gmail.com
License: UNKNOWN
Project-URL: Documentation, https://drf-keypair-permissions.readthedocs.io/
Platform: UNKNOWN
Classifier: Programming Language :: Python :: 3 :: Only
Classifier: Programming Language :: Python :: 3.6
Classifier: Programming Language :: Python :: 3.7
Classifier: Programming Language :: Python :: 3.8
Classifier: License :: OSI Approved :: ISC License (ISCL)
Classifier: Operating System :: OS Independent
Classifier: Development Status :: 5 - Production/Stable
Classifier: Intended Audience :: Developers
Classifier: Environment :: Web Environment
Classifier: Topic :: Software Development :: Libraries :: Python Modules
Classifier: Framework :: Django
Classifier: Framework :: Django :: 2.2
Classifier: Framework :: Django :: 3.0
Requires-Python: >=3.6
Requires-Dist: pycryptodome
Requires-Dist: fastecdsa
